whmcspy/__init__.py
whmcspy/api.py
whmcspy/exceptions.py
whmcspy-0.3.0.dist-info/DESCRIPTION.rst
whmcspy-0.3.0.dist-info/METADATA
whmcspy-0.3.0.dist-info/RECORD
whmcspy-0.3.0.dist-info/WHEEL
whmcspy-0.3.0.dist-info/metadata.json
whmcspy-0.3.0.dist-info/top_level.txt
