Metadata-Version: 2.0
Name: whmcspy
Version: 0.3.0
Summary: Python interface to the WHMCS API.
Home-page: https://github.com/Smoose-bv/whmcspy
Author: Smoose BV
License: GPL-3
Keywords: whmcs api library
Platform: UNKNOWN
Classifier: Programming Language :: Python :: 3
Classifier: License :: OSI Approved :: GNU General Public License v3 (GPLv3)
Classifier: Operating System :: OS Independent
Requires-Dist: requests (>=2.21.0)
